mechanician_openai/__init__.py
mechanician_openai/assistants_ai_connector.py
mechanician_openai/azure_openai_connector.py
mechanician_openai/chat_ai_connector.py
mechanician_openai/instruction_auto_tuner.py
mechanician_openai-0.1.3.dist-info/METADATA
mechanician_openai-0.1.3.dist-info/WHEEL
mechanician_openai-0.1.3.dist-info/top_level.txt
mechanician_openai-0.1.3.dist-info/RECORD
