Metadata-Version: 2.1
Name: mechanician-openai
Version: 0.1.3
Summary: Daring Mechanician AIConnectors for OpenAI Chat and Assistants APIs.
Home-page: https://github.com/liebke/mechanician
Author: David Edgar Liebke
Author-email: david@gmail.com
Requires-Dist: mechanician >=0.1.3
Requires-Dist: openai <2.0.0,>=1.11.0
